{
    "fluentMethods": true,
    "relationships": [],
    "fields": [
        {
            "fieldName": "name",
            "fieldType": "String",
            "fieldValidateRules": [
                "required"
            ]
        },
        {
            "fieldName": "surname",
            "fieldType": "String"
        },
        {
            "fieldName": "address",
            "fieldType": "String"
        },
        {
            "fieldName": "dateOfBirth",
            "fieldType": "ZonedDateTime"
        }
    ],
    "changelogDate": "20170212200021",
    "dto": "no",
    "service": "serviceClass",
    "entityTableName": "person",
    "pagination": "no"
}
